README.md
setup.cfg
setup.py
centos_package_cron/__init__.py
centos_package_cron/annoyance_check.py
centos_package_cron/annoyance_fetcher.py
centos_package_cron/command_line.py
centos_package_cron/db_base.py
centos_package_cron/db_session_fetcher.py
centos_package_cron/errata_fetcher.py
centos_package_cron/errata_item.py
centos_package_cron/mockable_execute.py
centos_package_cron/os_version_fetcher.py
centos_package_cron/package.py
centos_package_cron/package_checker.py
centos_package_cron/package_fetcher.py
centos_package_cron/package_parser.py
centos_package_cron/report_producer.py
centos_package_cron.egg-info/PKG-INFO
centos_package_cron.egg-info/SOURCES.txt
centos_package_cron.egg-info/dependency_links.txt
centos_package_cron.egg-info/entry_points.txt
centos_package_cron.egg-info/requires.txt
centos_package_cron.egg-info/top_level.txt