Metadata-Version: 1.1
Name: centos-package-cron
Version: 1.0.10
Summary: CentOS Package Update Utilities
Home-page: https://github.com/wied03/centos-package-cron
Author: Brady Wied
Author-email: support@bswtechconsulting.com
License: BSD 2-Clause
Download-URL: https://github.com/wied03/centos-package-cron/archive/releases/1.0.10.tar.gz
Platform: UNKNOWN
